streamsx/jms/__init__.py
streamsx/jms/_jms.py
streamsx.jms-0.3.3.dist-info/DESCRIPTION.rst
streamsx.jms-0.3.3.dist-info/LICENSE.txt
streamsx.jms-0.3.3.dist-info/METADATA
streamsx.jms-0.3.3.dist-info/RECORD
streamsx.jms-0.3.3.dist-info/WHEEL
streamsx.jms-0.3.3.dist-info/metadata.json
streamsx.jms-0.3.3.dist-info/top_level.txt
