Metadata-Version: 2.0
Name: streamsx.jms
Version: 0.3.3
Summary: JMS integration for IBM Streams
Home-page: https://github.com/IBMStreams/streamsx.jms
Author: IBM Streams @ github.com
Author-email: schulz2@de.ibm.com
License: Apache License - Version 2.0
Keywords: streams,ibmstreams,streaming,analytics,streaming-analytics,jms
Platform: UNKNOWN
Classifier: Development Status :: 2 - Pre-Alpha
Classifier: License :: OSI Approved :: Apache Software License
Classifier: Programming Language :: Python :: 3
Classifier: Programming Language :: Python :: 3.5
Classifier: Programming Language :: Python :: 3.6
Classifier: Programming Language :: Python :: 3.7
Requires-Dist: streamsx
Requires-Dist: streamsx.toolkits
